nlcpy_ve3_kernel/__init__.py
nlcpy_ve3_kernel/build_info.py
nlcpy_ve3_kernel/libnlcpy_profiling.so
nlcpy_ve3_kernel/libnlcpy_ve_kernel_common.so
nlcpy_ve3_kernel/libnlcpy_ve_kernel_fast_math.so
nlcpy_ve3_kernel/libnlcpy_ve_kernel_no_fast_math.so
nlcpy_ve3_kernel-3.0.1.dist-info/LICENSE
nlcpy_ve3_kernel-3.0.1.dist-info/METADATA
nlcpy_ve3_kernel-3.0.1.dist-info/WHEEL
nlcpy_ve3_kernel-3.0.1.dist-info/top_level.txt
nlcpy_ve3_kernel-3.0.1.dist-info/RECORD
