Metadata-Version: 2.1
Name: nlcpy-ve3-kernel
Version: 3.0.1
Summary: VE3 kernel for NLCPy
Home-page: https://github.com/SX-Aurora/nlcpy/
Author: NEC
Author-email: dev-nlcpy@sxarr.jp.nec.com
License: BSD 3-Clause
Project-URL: Bug Tracker, https://github.com/SX-Aurora/nlcpy/issues
Project-URL: Documentation, https://www.hpc.nec/documents/nlcpy/en/index.html
Keywords: nlcpy_ve3_kernel
Classifier: Development Status :: 5 - Production/Stable
Classifier: License :: OSI Approved :: BSD License
Classifier: Operating System :: POSIX :: Linux
Classifier: Programming Language :: C
Classifier: Programming Language :: Python :: 3 :: Only
Classifier: Topic :: Scientific/Engineering
Classifier: Topic :: Software Development
Requires-Python: <3.9,>=3.6
License-File: LICENSE
